streamix/__init__.py
streamix/streamix.py
streamix/utils.py
streamix-13.2.6.dist-info/METADATA
streamix-13.2.6.dist-info/WHEEL
streamix-13.2.6.dist-info/entry_points.txt
streamix-13.2.6.dist-info/top_level.txt
streamix-13.2.6.dist-info/RECORD
