Metadata-Version: 2.2
Name: streamix
Version: 13.2.6
Summary: Streamix: A tool for downloading YouTube videos and audio
Home-page: https://github.com/itanishajain/StreamIX
Author: Tanisha Jain
Author-email: itanishajain@gmail.com
Classifier: Programming Language :: Python :: 3
Classifier: License :: OSI Approved :: MIT License
Classifier: Operating System :: OS Independent
Requires-Dist: yt-dlp>=2023.3.4
Dynamic: author
Dynamic: author-email
Dynamic: classifier
Dynamic: description
Dynamic: description-content-type
Dynamic: home-page
Dynamic: requires-dist
Dynamic: summary
